serial_packets/__init__.py
serial_packets/_packets.py
serial_packets/client.py
serial_packets/packet_decoder.py
serial_packets/packet_encoder.py
serial_packets/packets.py
serial_packets/py.typed
serial_packets-0.2.3.dist-info/METADATA
serial_packets-0.2.3.dist-info/WHEEL
serial_packets-0.2.3.dist-info/licenses/LICENSE
serial_packets-0.2.3.dist-info/RECORD
